README.md
airconditioner.py
constructors.py
setup.cfg
setup.py
airconditioner.egg-info/PKG-INFO
airconditioner.egg-info/SOURCES.txt
airconditioner.egg-info/dependency_links.txt
airconditioner.egg-info/requires.txt
airconditioner.egg-info/top_level.txt